ape_foundry/__init__.py
ape_foundry/constants.py
ape_foundry/exceptions.py
ape_foundry/provider.py
ape_foundry/py.typed
ape_foundry/trace.py
ape_foundry/version.py
ape_foundry-0.8.11.dist-info/licenses/LICENSE
ape_foundry-0.8.11.dist-info/METADATA
ape_foundry-0.8.11.dist-info/WHEEL
ape_foundry-0.8.11.dist-info/top_level.txt
ape_foundry-0.8.11.dist-info/RECORD
